[
    {
        "paramName": "AppKey",
        "paramCode": "AppKey",
        "isNull": "1",
        "sort": 1,
        "paramType": "0",
        "remark": "Public Parameter",
        "parentSeq": -2
    },
    {
        "paramName": "API接口名称",
        "paramCode": "BusiCode",
        "isNull": "0",
        "sort": 2,
        "paramType": "0",
        "remark": "Public Parameter",
        "parentSeq": -2
    },
    {
        "paramName": "交易流水号",
        "paramCode": "TransactionID",
        "isNull": "1",
        "sort": 3,
        "paramType": "0",
        "remark": "Public Parameter",
        "parentSeq": -2
    },
    {
        "paramName": "请求时间",
        "paramCode": "ReqTime",
        "isNull": "1",
        "sort": 4,
        "paramType": "0",
        "remark": "Public Parameter",
        "parentSeq": -2
    },
    {
        "paramName": "签名字符串",
        "paramCode": "Sign",
        "isNull": "1",
        "sort": 5,
        "paramType": "0",
        "remark": "Public Parameter",
        "parentSeq": -2
    },
    {
        "paramName": "AccessToken",
        "paramCode": "AccessToken",
        "isNull": "1",
        "sort": 6,
        "paramType": "0",
        "remark": "Public Parameter",
        "parentSeq": -2
    },
    {
        "paramName": "接口版本",
        "paramCode": "Version",
        "isNull": "1",
        "sort": 7,
        "paramType": "0",
        "remark": "Public Parameter",
        "parentSeq": -2
    },
    {
        "paramName": "落地方系统",
        "paramCode": "DstSysID",
        "isNull": "1",
        "sort": 8,
        "paramType": "0",
        "remark": "Public Parameter",
        "parentSeq": -2
    },
    {
        "paramName": "租户id",
        "paramCode": "TenantId",
        "isNull": "1",
        "sort": 9,
        "paramType": "0",
        "remark": "Public Parameter",
        "parentSeq": -2
    },
    {
        "paramName": "受理地市",
        "paramCode": "AcceptRegionCode",
        "isNull": "1",
        "sort": 10,
        "paramType": "0",
        "remark": "Public Parameter",
        "parentSeq": -2
    },
    {
        "paramName": "一次性费用",
        "paramCode": "ChargeFlag",
        "isNull": "1",
        "sort": 11,
        "paramType": "0",
        "remark": "Public Parameter",
        "parentSeq": -2
    },
    {
        "paramName": "受理渠道类型",
        "paramCode": "AcceptChannelType",
        "isNull": "0",
        "sort": 12,
        "paramType": "0",
        "remark": "Public Parameter",
        "parentSeq": -2
    },
    {
        "paramName": "受理渠道",
        "paramCode": "AcceptChannelCode",
        "isNull": "1",
        "sort": 13,
        "paramType": "0",
        "remark": "Public Parameter",
        "parentSeq": -2
    },
    {
        "paramName": "是否发送通知",
        "paramCode": "NotifyFlag",
        "isNull": "1",
        "sort": 14,
        "paramType": "0",
        "remark": "Public Parameter",
        "parentSeq": -2
    },
    {
        "paramName": "受理员工",
        "paramCode": "AcceptStaffId",
        "isNull": "0",
        "sort": 15,
        "paramType": "0",
        "remark": "Public Parameter",
        "parentSeq": -2
    }
]
